idem_azurerm/conf.py
idem_azurerm/scripts.py
idem_azurerm/version.py
idem_azurerm/acct/azurerm_keyvault.py
idem_azurerm/exec/azurerm/utils.py
idem_azurerm/exec/azurerm/application_insights/component.py
idem_azurerm/exec/azurerm/authorization/permission.py
idem_azurerm/exec/azurerm/authorization/provider.py
idem_azurerm/exec/azurerm/authorization/role.py
idem_azurerm/exec/azurerm/compute/availability_set.py
idem_azurerm/exec/azurerm/compute/dedicated_host_group.py
idem_azurerm/exec/azurerm/compute/disk.py
idem_azurerm/exec/azurerm/compute/image.py
idem_azurerm/exec/azurerm/compute/proximity_placement_group.py
idem_azurerm/exec/azurerm/compute/ssh_public_key.py
idem_azurerm/exec/azurerm/compute/virtual_machine.py
idem_azurerm/exec/azurerm/compute/virtual_machine_extension.py
idem_azurerm/exec/azurerm/compute/virtual_machine_extension_image.py
idem_azurerm/exec/azurerm/compute/virtual_machine_image.py
idem_azurerm/exec/azurerm/compute/virtual_machine_size.py
idem_azurerm/exec/azurerm/containerinstance/container.py
idem_azurerm/exec/azurerm/containerinstance/group.py
idem_azurerm/exec/azurerm/containerregistry/registry.py
idem_azurerm/exec/azurerm/containerregistry/replication.py
idem_azurerm/exec/azurerm/containerregistry/run.py
idem_azurerm/exec/azurerm/containerregistry/task.py
idem_azurerm/exec/azurerm/containerregistry/webhook.py
idem_azurerm/exec/azurerm/dns/record_set.py
idem_azurerm/exec/azurerm/dns/zone.py
idem_azurerm/exec/azurerm/graphrbac/client.py
idem_azurerm/exec/azurerm/graphrbac/service_principal.py
idem_azurerm/exec/azurerm/graphrbac/user.py
idem_azurerm/exec/azurerm/keyvault/key.py
idem_azurerm/exec/azurerm/keyvault/secret.py
idem_azurerm/exec/azurerm/keyvault/vault.py
idem_azurerm/exec/azurerm/log_analytics/workspace.py
idem_azurerm/exec/azurerm/managed_service_identity/user_assigned_identity.py
idem_azurerm/exec/azurerm/managementgroup/operations.py
idem_azurerm/exec/azurerm/monitor/diagnostic_setting.py
idem_azurerm-4.0.0.dist-info/LICENSE
idem_azurerm-4.0.0.dist-info/METADATA
idem_azurerm-4.0.0.dist-info/WHEEL
idem_azurerm-4.0.0.dist-info/top_level.txt
idem_azurerm-4.0.0.dist-info/RECORD
