Metadata-Version: 2.1
Name: idem-azurerm
Version: 4.0.0
Summary: Idem language provider for Azure
Home-page: https://github.com/eitrtechnologies/idem-azurerm
Author: EITR Technologies, LLC
Author-email: devops@eitr.tech
License: UNKNOWN
Platform: UNKNOWN
Classifier: Operating System :: OS Independent
Classifier: Programming Language :: Python
Classifier: Programming Language :: Python :: 3.6
Classifier: Programming Language :: Python :: 3.7
Classifier: Programming Language :: Python :: 3.8
Classifier: Development Status :: 5 - Production/Stable
Requires-Python: >=3.6
Requires-Dist: acct (==2.3)
Requires-Dist: azure-common (==1.1.25)
Requires-Dist: azure-core (==1.8.1)
Requires-Dist: azure-graphrbac (==0.61.1)
Requires-Dist: azure-identity (==1.4.0)
Requires-Dist: azure-keyvault-keys (==4.2.0)
Requires-Dist: azure-keyvault-secrets (==4.2.0)
Requires-Dist: azure-mgmt-applicationinsights (==0.2.0)
Requires-Dist: azure-mgmt-authorization (==0.61.0)
Requires-Dist: azure-mgmt-compute (==13.0.0)
Requires-Dist: azure-mgmt-containerinstance (==2.0.0)
Requires-Dist: azure-mgmt-containerregistry (==3.0.0rc14)
Requires-Dist: azure-mgmt-dns (==3.0.0)
Requires-Dist: azure-mgmt-keyvault (==2.2.0)
Requires-Dist: azure-mgmt-loganalytics (==0.7.0)
Requires-Dist: azure-mgmt-managementgroups (==0.2.0)
Requires-Dist: azure-mgmt-monitor (==0.11.0)
Requires-Dist: azure-mgmt-msi (==1.0.0)
Requires-Dist: azure-mgmt-network (==11.0.0)
Requires-Dist: azure-mgmt-rdbms (==2.2.0)
Requires-Dist: azure-mgmt-redis (==6.0.0)
Requires-Dist: azure-mgmt-resource (==8.0.0)
Requires-Dist: azure-mgmt-storage (==11.1.0)
Requires-Dist: azure-mgmt-web (==0.47.0)
Requires-Dist: azure-storage-blob (==12.3.2)
Requires-Dist: dict-toolbox (==1.9)
Requires-Dist: idem (==7.4)
Requires-Dist: msrest (==0.6.19)
Requires-Dist: msrestazure (==0.6.4)
Requires-Dist: pop-config (==6.10)
Requires-Dist: pop (==13.2)
Requires-Dist: takara (==1.2)
Requires-Dist: websocket-client (==0.56.0)
